s7/__init__.py
s7/exceptions.py
s7/factories/__init__.py
s7/factories/datasource_factory.py
s7/factories/entity_factory.py
s7/factories/generated_classes.py
s7/graph/README.md
s7/graph/__init__.py
s7/graph/utils.py
s7/oteapi_plugin/__init__.py
s7/oteapi_plugin/models.py
s7/oteapi_plugin/soft7_function.py
s7/oteapi_plugin/yaml_parser.py
s7/pydantic_models/__init__.py
s7/pydantic_models/_utils.py
s7/pydantic_models/datasource.py
s7/pydantic_models/oteapi.py
s7/pydantic_models/soft7_entity.py
s7/pydantic_models/soft7_instance.py
soft7-0.4.0.dist-info/entry_points.txt
soft7-0.4.0.dist-info/licenses/LICENSE
soft7-0.4.0.dist-info/WHEEL
soft7-0.4.0.dist-info/METADATA
soft7-0.4.0.dist-info/RECORD
