Metadata-Version: 2.4
Name: soft7
Version: 0.4.0
Summary: SOFT7 semantic interoperability framework.
Keywords: interoperability,semantic
Author-email: Thomas Fjæstad Hagelien <thomas.f.hagelien@sintef.no>, Casper Welzel Andersen <casper.w.andersen@sintef.no>, Treesa Rose Joseph <treesa.joseph@sintef.no>
Requires-Python: ~=3.10
Classifier: Development Status :: 2 - Pre-Alpha
Classifier: License :: OSI Approved :: MIT License
Classifier: Programming Language :: Python :: 3
Classifier: Programming Language :: Python :: 3.10
Classifier: Programming Language :: Python :: 3.11
Classifier: Programming Language :: Python :: 3.12
Classifier: Programming Language :: Python :: 3.13
Classifier: Natural Language :: English
Classifier: Operating System :: OS Independent
License-File: LICENSE
Requires-Dist: httpx>=0.28.1,<1
Requires-Dist: oteapi-core~=1.0
Requires-Dist: otelib~=1.0
Requires-Dist: pyyaml~=6.0
Requires-Dist: pre-commit~=4.2 ; extra == "dev"
Requires-Dist: soft7[docs, graph, testing] ; extra == "dev"
Requires-Dist: myst-nb~=1.2 ; extra == "docs"
Requires-Dist: pydata-sphinx-theme~=0.16.1 ; extra == "docs"
Requires-Dist: sphinx~=8.1 ; extra == "docs"
Requires-Dist: jinja2~=3.1 ; extra == "graph"
Requires-Dist: rdflib~=7.1 ; extra == "graph"
Requires-Dist: sparqlwrapper~=2.0 ; extra == "graph"
Requires-Dist: pytest~=8.3 ; extra == "testing"
Requires-Dist: pytest-cov~=6.1 ; extra == "testing"
Requires-Dist: pytest-httpx~=0.35.0 ; extra == "testing"
Requires-Dist: requests-mock~=1.12 ; extra == "testing"
Requires-Dist: soft7[graph] ; extra == "testing"
Project-URL: Changelog, https://github.com/SINTEF/soft7/blob/main/CHANGELOG.md
Project-URL: Documentation, https://SINTEF.github.io/soft7
Project-URL: Home, https://github.com/SINTEF/soft7
Project-URL: Issue Tracker, https://github.com/SINTEF/soft7/issues
Project-URL: Package, https://pypi.org/project/soft7
Project-URL: Source, https://github.com/SINTEF/soft7
Provides-Extra: dev
Provides-Extra: docs
Provides-Extra: graph
Provides-Extra: testing
